cache_gs/__init__.py
cache_gs/cache_gs.py
cache_gs/cache_classes/__init__.py
cache_gs/cache_classes/cache_data.py
cache_gs/cache_classes/cache_data_file.py
cache_gs/cache_classes/file_cache.py
cache_gs/cache_classes/memory_cache.py
cache_gs/cache_classes/redis_cache.py
cache_gs/cache_classes/sqlite_cache.py
cache_gs/interfaces/__init__.py
cache_gs/interfaces/serialization.py
cache_gs/interfaces/super_cache.py
cache_gs/utils/__init__.py
cache_gs/utils/filesystem.py
cache_gs/utils/logging.py
cache_gs/utils/timestamp.py
cache_gs/utils/types.py
tests/cache_classes/__init__.py
tests/cache_classes/test_cache_data.py
tests/cache_classes/test_cache_data_file.py
tests/cache_classes/test_cache_gs.py
tests/cache_classes/test_file_cache.py
tests/cache_classes/test_memory_cache.py
tests/cache_classes/test_redis_cache.py
tests/cache_classes/test_sqlite_cache.py
tests/interfaces/__init__.py
tests/interfaces/test_serialization.py
tests/interfaces/test_super_cache.py
tests/real_tests/__init__.py
tests/real_tests/test_real_file_cache.py
tests/real_tests/test_real_sqlite_cache.py
tests/utils/__init__.py
tests/utils/test_filesystem.py
tests/utils/test_log.py
tests/utils/test_timestamp.py
tests/utils/test_types.py
cache_guiosoft-0.0.7.dist-info/LICENSE
cache_guiosoft-0.0.7.dist-info/METADATA
cache_guiosoft-0.0.7.dist-info/WHEEL
cache_guiosoft-0.0.7.dist-info/top_level.txt
cache_guiosoft-0.0.7.dist-info/zip-safe
cache_guiosoft-0.0.7.dist-info/RECORD
