Metadata-Version: 2.1
Name: cache-guiosoft
Version: 0.0.7
Summary: UNKNOWN
Home-page: https://github.com/guionardo/py-cache-guiosoft
Author: Guionardo Furlan
Author-email: guionardo@gmail.com
License: MIT
Project-URL: Documentation, https://github.com/guionardo/py-cache-guiosoft/wiki
Project-URL: Source, https://github.com/guionardo/py-cache-guiosoft
Keywords: cache
Platform: UNKNOWN
Classifier: Development Status :: 4 - Beta
Classifier: Environment :: Console
Classifier: Intended Audience :: Developers
Classifier: License :: OSI Approved :: MIT License
Classifier: Topic :: Software Development :: Build Tools
Classifier: Topic :: Utilities
Classifier: Programming Language :: Python
Classifier: Programming Language :: Python :: 3.6
Classifier: Programming Language :: Python :: 3.7
Classifier: Programming Language :: Python :: 3.8
Requires-Python: >=3.6.*
Requires-Dist: redis
